Metadata-Version: 1.0
Name: squarenum-package
Version: 0.1
Summary: Square of a number
Home-page: UNKNOWN
Author: Salomon Marquez
Author-email: phd.smarquez@gmail.com
License: UNKNOWN
Platform: UNKNOWN
